apsbss/__init__.py
apsbss/_version.py
apsbss/apsbss.adl
apsbss/apsbss.db
apsbss/apsbss.py
apsbss/apsbss.ui
apsbss/apsbss_ioc.sh
apsbss/apsbss_makedb.py
apsbss/apsbss_ophyd.py
apsbss/bss_dm.py
apsbss/bss_is.py
apsbss/core.py
apsbss/server_interface.py
apsbss/text_search.py
apsbss/tests/__init__.py
apsbss/tests/_core.py
apsbss/tests/conftest.py
apsbss/tests/test_apsbss.py
apsbss/tests/test_apsbss_get.py
apsbss/tests/test_apsbss_list.py
apsbss/tests/test_apsbss_ophyd.py
apsbss/tests/test_bss_dm.py
apsbss/tests/test_bss_is.py
apsbss/tests/test_core.py
apsbss/tests/test_server_interface.py
apsbss/tests/test_text_search.py
apsbss/tests/data/dm-btr-64057.yml
apsbss/tests/data/dm-btr-77056.yml
apsbss/tests/data/dm-btr-78243.yml
apsbss/tests/data/dm-btr-78544.yml
apsbss/tests/data/dm-esaf-226319.yml
apsbss/tests/data/is-activity-78544.yml
apsbss/tests/data/is-btr-77056.yml
apsbss/tests/data/is-btr-78544.yml
apsbss/tests/data/user.yml
apsbss-2.0.1.dist-info/licenses/LICENSE.txt
apsbss-2.0.1.dist-info/METADATA
apsbss-2.0.1.dist-info/WHEEL
apsbss-2.0.1.dist-info/entry_points.txt
apsbss-2.0.1.dist-info/top_level.txt
apsbss-2.0.1.dist-info/RECORD
