Metadata-Version: 2.4
Name: apsbss
Version: 2.0.1
Summary: Get information from APS Beamline Scheduling System.
Author-email: Pete Jemian <prjemian+apsbss@gmail.com>
Maintainer-email: Pete Jemian <prjemian+apsbss@gmail.com>
License: Copyright (c) 2017-2025, UChicago Argonne, LLC
Project-URL: Bug Tracker, https://github.com/BCDA-APS/apsbss/issues
Project-URL: Homepage, https://BCDA-APS.github.io/apsbss
Project-URL: Release Notes, https://github.com/BCDA-APS/apsbss/blob/main/CHANGES.rst
Project-URL: Source Code, https://github.com/BCDA-APS/apsbss
Keywords: APS,BSS,ESAF,Proposal,EPICS
Classifier: Development Status :: 5 - Production/Stable
Classifier: Environment :: Console
Classifier: Intended Audience :: Science/Research
Classifier: License :: Freely Distributable
Classifier: License :: Public Domain
Classifier: Programming Language :: Python
Classifier: Programming Language :: Python :: 3
Classifier: Topic :: Scientific/Engineering
Classifier: Topic :: Scientific/Engineering :: Astronomy
Classifier: Topic :: Scientific/Engineering :: Bio-Informatics
Classifier: Topic :: Scientific/Engineering :: Chemistry
Classifier: Topic :: Scientific/Engineering :: Information Analysis
Classifier: Topic :: Scientific/Engineering :: Interface Engine/Protocol Translator
Classifier: Topic :: Scientific/Engineering :: Mathematics
Classifier: Topic :: Scientific/Engineering :: Physics
Classifier: Topic :: Software Development :: Embedded Systems
Classifier: Topic :: Software Development :: Libraries :: Python Modules
Classifier: Topic :: Scientific/Engineering :: Visualization
Classifier: Topic :: Software Development
Classifier: Topic :: Utilities
Requires-Python: >=3.9
License-File: LICENSE.txt
Requires-Dist: bluesky
Requires-Dist: databroker
Requires-Dist: ophyd
Requires-Dist: pyRestTable
Requires-Dist: pyyaml
Requires-Dist: requests
Requires-Dist: spec2nexus
Requires-Dist: whoosh
Provides-Extra: dev
Requires-Dist: build; extra == "dev"
Requires-Dist: caproto<1.2.0; extra == "dev"
Requires-Dist: coverage; extra == "dev"
Requires-Dist: ipython; extra == "dev"
Requires-Dist: isort; extra == "dev"
Requires-Dist: mypy; extra == "dev"
Requires-Dist: pre-commit; extra == "dev"
Requires-Dist: pyepics; extra == "dev"
Requires-Dist: pytest; extra == "dev"
Requires-Dist: ruff; extra == "dev"
Provides-Extra: doc
Requires-Dist: ipykernel; extra == "doc"
Requires-Dist: jinja2; extra == "doc"
Requires-Dist: pydata-sphinx-theme; extra == "doc"
Requires-Dist: pygments-ipython-console; extra == "doc"
Requires-Dist: pygments; extra == "doc"
Requires-Dist: sphinx-design; extra == "doc"
Requires-Dist: sphinx-tabs; extra == "doc"
Requires-Dist: sphinx; extra == "doc"
Provides-Extra: all
Requires-Dist: apsbss[dev,doc]; extra == "all"
Dynamic: license-file
